webassets_webpack/__init__.py
webassets_webpack/tests/__init__.py
webassets_webpack/tests/test_webpack.py
webassets_webpack-0.1.6.dist-info/METADATA
webassets_webpack-0.1.6.dist-info/RECORD
webassets_webpack-0.1.6.dist-info/WHEEL
webassets_webpack-0.1.6.dist-info/top_level.txt
