Metadata-Version: 2.1
Name: webassets-webpack
Version: 0.1.6
Summary: Webpack filter for webassets
Home-page: https://github.com/suryakencana/webassets-webpack
Author: Nanang Suryadi
Author-email: nanang.jobs@gmail.com
License: MIT
Download-URL: https://github.com/suryakencana/webassets-webpack/archive/0.1.0.tar.gz
Keywords: webpack,webassets,django assets,pyramid assets
Platform: UNKNOWN
Classifier: Development Status :: 5 - Production/Stable
Classifier: Intended Audience :: Developers
Classifier: License :: OSI Approved :: MIT License
Classifier: Programming Language :: Python :: 2.7
Classifier: Programming Language :: Python :: 3.3
Classifier: Programming Language :: Python :: 3.4
Classifier: Programming Language :: Python :: 3.5
Classifier: Programming Language :: Python :: 3.6
Requires-Dist: webassets
